myleadcli/__init__.py
myleadcli/__main__.py
myleadcli/main.py
myleadcli/ml.py
myleadcli/models.py
myleadcli/plotting.py
myleadcli/tables.py
myleadcli/utils.py
myleadcli-0.1.3.dist-info/entry_points.txt
myleadcli-0.1.3.dist-info/LICENSE
myleadcli-0.1.3.dist-info/METADATA
myleadcli-0.1.3.dist-info/WHEEL
myleadcli-0.1.3.dist-info/RECORD
