Metadata-Version: 2.1
Name: myleadcli
Version: 0.1.3
Summary: 
Home-page: https://github.com/ikosmala/mylead-cli
License: MIT
Keywords: test,dependencies,documentation
Author: Iwo
Author-email: kosmala.iwo@gmail.com
Requires-Python: >=3.11,<4.0
Classifier: License :: OSI Approved :: MIT License
Classifier: Programming Language :: Python :: 3
Classifier: Programming Language :: Python :: 3.11
Classifier: Programming Language :: Python :: 3.12
Requires-Dist: asyncio (>=3.4.3,<4.0.0)
Requires-Dist: httpx[http2] (>=0.25.0,<0.26.0)
Requires-Dist: orjson (>=3.9.7,<4.0.0)
Requires-Dist: pandas (>=2.1.0,<3.0.0)
Requires-Dist: plotly (>=5.16.1,<6.0.0)
Requires-Dist: pydantic (>=2.3.0,<3.0.0)
Requires-Dist: python-dotenv (>=1.0.0,<2.0.0)
Requires-Dist: tenacity (>=8.2.3,<9.0.0)
Requires-Dist: typer[all] (>=0.9.0,<0.10.0)
Project-URL: Repository, https://github.com/ikosmala/mylead-cli
